{"name":"checkboxTest","id":"webelements.HandlingCheckboxes:checkboxTest","testCaseName":"webelements.HandlingCheckboxes","userStory":{"id":"webelements.HandlingCheckboxes","storyName":"Handling checkboxes","storyClassName":"webelements.HandlingCheckboxes","path":"webelements","type":"story"},"featureTag":{"name":"Webelements/Handling checkboxes","type":"story","displayName":"Webelements/Handling checkboxes"},"title":"Checkbox test","tags":[{"name":"Webelements/Handling checkboxes","type":"story","displayName":"Webelements/Handling checkboxes"}],"startTime":"2021-10-01T09:21:31.581810100+05:30[Asia/Calcutta]","duration":15439,"projectKey":"","sessionId":"519825116449ddc6c43a57658360a6f1","driver":"chrome","isManualTestingUpToDate":false,"manual":false,"testSource":"JUnit","result":"SUCCESS"}